cpmf_uisor/__init__.py
cpmf_uisor/adapter_element_V6.py
cpmf_uisor/adapter_screen_V2.py
cpmf_uisor/cli.py
cpmf_uisor/discovery.py
cpmf_uisor/formatters.py
cpmf_uisor/git.py
cpmf_uisor/models.py
cpmf_uisor/parser.py
cpmf_uisor/rules.py
cpmf_uisor/templates.py
cpmf_uisor-0.1.2.dist-info/METADATA
cpmf_uisor-0.1.2.dist-info/WHEEL
cpmf_uisor-0.1.2.dist-info/entry_points.txt
cpmf_uisor-0.1.2.dist-info/RECORD
