Metadata-Version: 2.4
Name: cpmf-uisor
Version: 0.1.2
Summary: UiPath Object Repository CLI Tool
Requires-Python: >=3.11
Requires-Dist: jinja2>=3.0.0
Requires-Dist: pillow>=10.0.0
Requires-Dist: typer>=0.9.0
Provides-Extra: dev
Requires-Dist: black>=24.0.0; extra == 'dev'
Requires-Dist: ruff>=0.1.0; extra == 'dev'
